{
    "Ar36": {
        "error": 0.0009322217647912437, 
        "filter_outliers_dict": {
            "filter_outliers": true, 
            "iterations": 2, 
            "std_devs": 2
        }, 
        "fit": "Parabolic", 
        "value": 0.19168460079556143
    }, 
    "Ar37": {
        "error": 0.01188973890938291, 
        "filter_outliers_dict": {
            "filter_outliers": true, 
            "iterations": 2, 
            "std_devs": 2
        }, 
        "fit": "linear", 
        "value": 4.0663594492032455
    }, 
    "Ar38": {
        "error": 0.013349220159145761, 
        "filter_outliers_dict": {
            "filter_outliers": true, 
            "iterations": 2, 
            "std_devs": 2
        }, 
        "fit": "linear", 
        "value": 0.23130192848813125
    }, 
    "Ar39": {
        "error": 0.025834144941254453, 
        "filter_outliers_dict": {
            "filter_outliers": true, 
            "iterations": 2, 
            "std_devs": 2
        }, 
        "fit": "Parabolic", 
        "value": 14.996573839460767
    }, 
    "Ar40": {
        "error": 0.03687090645543265, 
        "filter_outliers_dict": {
            "filter_outliers": true, 
            "iterations": 2, 
            "std_devs": 2
        }, 
        "fit": "Parabolic", 
        "value": 234.05398818085996
    }
}