{
    "Ar36": {
        "error": 0.0010963906407724514, 
        "filter_outliers_dict": {
            "filter_outliers": true, 
            "iterations": 2, 
            "std_devs": 2
        }, 
        "fit": "Parabolic", 
        "value": 0.29733386196939904
    }, 
    "Ar37": {
        "error": 0.011370870892123467, 
        "filter_outliers_dict": {
            "filter_outliers": true, 
            "iterations": 2, 
            "std_devs": 2
        }, 
        "fit": "linear", 
        "value": -0.5507059040960982
    }, 
    "Ar38": {
        "error": 0.012973170304018436, 
        "filter_outliers_dict": {
            "filter_outliers": true, 
            "iterations": 2, 
            "std_devs": 2
        }, 
        "fit": "linear", 
        "value": 0.13456895274332137
    }, 
    "Ar39": {
        "error": 0.023636267643139683, 
        "filter_outliers_dict": {
            "filter_outliers": true, 
            "iterations": 2, 
            "std_devs": 2
        }, 
        "fit": "Parabolic", 
        "value": 11.697956365477452
    }, 
    "Ar40": {
        "error": 0.030117060807209665, 
        "filter_outliers_dict": {
            "filter_outliers": true, 
            "iterations": 2, 
            "std_devs": 2
        }, 
        "fit": "Parabolic", 
        "value": 157.48746680594797
    }
}